lys/__init__.py
lys-1.0.dist-info/METADATA
lys-1.0.dist-info/WHEEL
lys-1.0.dist-info/top_level.txt
lys-1.0.dist-info/RECORD
