Metadata-Version: 2.1
Name: lys
Version: 1.0
Summary: Simple HTML templating for Python
Home-page: http://github.com/mdamien/lys
Author: Damien MARIÉ
Author-email: damien@dam.io
License: MIT
Platform: UNKNOWN
Classifier: Development Status :: 5 - Production/Stable
Classifier: Intended Audience :: Developers
Classifier: Natural Language :: English
Classifier: License :: OSI Approved :: MIT License
Classifier: Programming Language :: Python :: 2
Classifier: Programming Language :: Python :: 3
